[
    {
        "title": "MLB – Minnesota Twins vs Chicago White Sox",
        "time": "12:30",
        "category": "Futbol",
        "status": "En vivo",
        "link": "https://la14hd.com/vivo/canales.php?stream=espn5",
        "language": "español"
    },
    {
        "title": "MLB – Minnesota Twins vs Chicago White Sox",
        "time": "12:30",
        "category": "Futbol",
        "status": "En vivo",
        "link": "https://rojadirectatve.com/sw3.html?get=https://rojadirectatve.com/repro/espn5tv.html",
        "language": ""
    },
    {
        "title": "Amistoso: Albania vs Israel",
        "time": "13:00",
        "category": "Futbol",
        "status": "En vivo",
        "link": "https://la14hd.com/vivo/canales.php?stream=disney2",
        "language": "Español"
    },
    {
        "title": "Torneo Maurice Revello Sub-20 : Costa de Marfil vs Venezuela",
        "time": "11:30",
        "category": "Futbol",
        "status": "En vivo",
        "link": "https://la14hd.com/vivo/canales.php?stream=foxdeportes",
        "language": "Español"
    }
]
